README.rst
setup.py
Hellas/Athens.py
Hellas/Delphi.py
Hellas/Olympia.py
Hellas/Pella.py
Hellas/Sparta.py
Hellas/Thebes.py
Hellas/__init__.py
Hellas.egg-info/PKG-INFO
Hellas.egg-info/SOURCES.txt
Hellas.egg-info/dependency_links.txt
Hellas.egg-info/not-zip-safe
Hellas.egg-info/top_level.txt
Hellas/tests/__init__.py
Hellas/tests/tests.py