Metadata-Version: 1.1
Name: Hellas
Version: 1.0.16
Summary: Some basic python utilities (classes, functions, snippets)
Home-page: https://github.com/nickmilon/Hellas
Author: @nickmilon
Author-email: nickmilon/gmail/com
License: GPL3
Download-URL: https://github.com/nickmilon/Hellas/tarball/master
Keywords: utilities,snippets,librarypython
Platform: UNKNOWN
Classifier: Development Status :: 5 - Production/Stable
Classifier: Intended Audience :: Developers
Classifier: License :: OSI Approved :: Apache Software License
Classifier: Operating System :: MacOS :: MacOS X
Classifier: Operating System :: Microsoft :: Windows
Classifier: Operating System :: POSIX
Classifier: Programming Language :: Python :: 2.7
Classifier: Programming Language :: Python :: 3.4
Classifier: Topic :: Software Development :: Libraries
